translate/__init__.py
translate/translate.py
terminal_translator-1.0.1.dist-info/LICENSE
terminal_translator-1.0.1.dist-info/METADATA
terminal_translator-1.0.1.dist-info/WHEEL
terminal_translator-1.0.1.dist-info/entry_points.txt
terminal_translator-1.0.1.dist-info/top_level.txt
terminal_translator-1.0.1.dist-info/RECORD
